zindex_py.cpython-310-x86_64-linux-gnu.so
zindex_py/bin/zindex
zindex_py/bin/zq
zindex_py/lib/libzindex_core.so
zindex_py/lib/zindex_py.cpython-310-x86_64-linux-gnu.so
zindex_py/lib/cmake/zindex/zindex-config-version.cmake
zindex_py/lib/cmake/zindex/zindex-config.cmake
zindex_py/lib/cmake/zindex/zindex-targets-release.cmake
zindex_py/lib/cmake/zindex/zindex-targets.cmake
zindex_py.libs/libzindex_core-1875c354.so
zindex_py-0.0.7.dist-info/AUTHORS
zindex_py-0.0.7.dist-info/LICENSE
zindex_py-0.0.7.dist-info/METADATA
zindex_py-0.0.7.dist-info/WHEEL
zindex_py-0.0.7.dist-info/top_level.txt
zindex_py-0.0.7.dist-info/RECORD
