Metadata-Version: 2.4
Name: zindex_py
Version: 0.0.7
Summary: Indexer for GZIP specially built for DLIO Profiler.
Home-page: https://github.com/hariharan-devarajan/zindex
Author: Hariharan Devarajan (Hari)
Project-URL: Bug Reports, https://github.com/hariharan-devarajan/zindex/issues
Project-URL: Source, https://github.com/hariharan-devarajan/zindex
Keywords: profiler,deep learning,I/O,benchmark,NPZ,pytorch benchmark,tensorflow benchmark
Classifier: Development Status :: 3 - Alpha
Classifier: Intended Audience :: Science/Research
Classifier: Topic :: Software Development :: Build Tools
Classifier: License :: OSI Approved :: MIT License
Classifier: Programming Language :: Python :: 3.7
Classifier: Programming Language :: Python :: 3.8
Classifier: Programming Language :: Python :: 3.9
Classifier: Programming Language :: Python :: 3.10
Classifier: Programming Language :: Python :: 3.11
Classifier: Programming Language :: Python :: 3.12
Classifier: Programming Language :: Python :: 3 :: Only
Requires-Python: >=3.7
License-File: LICENSE
License-File: AUTHORS
Requires-Dist: pybind11
Requires-Dist: setuptools>=64
Requires-Dist: wheel
Requires-Dist: cmake>=3.12
Provides-Extra: test
Requires-Dist: pytest>=6.0; extra == "test"
Dynamic: author
Dynamic: classifier
Dynamic: description
Dynamic: description-content-type
Dynamic: home-page
Dynamic: keywords
Dynamic: license-file
Dynamic: project-url
Dynamic: provides-extra
Dynamic: requires-dist
Dynamic: requires-python
Dynamic: summary
